pychunom/__init__.py
pychunom/dict/chunom.json
pychunom/dict/chunom.ocd2
pychunom-0.2.dist-info/METADATA
pychunom-0.2.dist-info/WHEEL
pychunom-0.2.dist-info/top_level.txt
pychunom-0.2.dist-info/RECORD
