Metadata-Version: 2.1
Name: pychunom
Version: 0.2
Summary: Convert Quoc Ngu to Chu Nom
Home-page: https://github.com/CjangCjengh/pychunom/
Download-URL: https://github.com/CjangCjengh/pychunom/archive/master.zip
Author: CjangCjengh
Author-email: 126621566zz@gmail.com
License: MIT
Keywords: Vietnamese,Chunom
Classifier: Development Status :: 3 - Alpha
Classifier: Intended Audience :: Developers
Classifier: Topic :: Software Development :: Build Tools
Classifier: License :: OSI Approved :: MIT License
Classifier: Programming Language :: Python :: 3
Requires-Dist: opencc
